mwwlean_email_scraper/__init__.py
mwwlean_email_scraper/main.py
mwwlean_email_scraper-0.7.dist-info/LICENSE
mwwlean_email_scraper-0.7.dist-info/METADATA
mwwlean_email_scraper-0.7.dist-info/WHEEL
mwwlean_email_scraper-0.7.dist-info/entry_points.txt
mwwlean_email_scraper-0.7.dist-info/top_level.txt
mwwlean_email_scraper-0.7.dist-info/RECORD
