Metadata-Version: 2.1
Name: mwwlean-email-scraper
Version: 0.7
Summary: A Python tool that extracts public email addresses from websites.
Author: mwwlean
License-File: LICENSE
Requires-Dist: pyfiglet
Requires-Dist: requests
